Workbook

Sheet Instructions
B1: EDU AI Agent Suite — ROI / TCO Calculator
B2: For use in customer conversations. All inputs are editable — the numbers are yours.
B4: HOW TO USE THIS CALCULATOR
B5: 1. Start on the 'Institution Profile' tab. Enter your institution's basic profile — enrollment, staffing, current volumes, and costs. These drive the calculations on every other sheet.
B6: 2. Go to 'Agent ROI'. Toggle each agent on or off (Y/N). Adjust the volume inputs and deflection-rate assumptions for each agent you plan to deploy. The labor savings and value calculations update automatically.
B7: 3. Review 'AWS TCO'. Enter estimated monthly interaction volumes for each service tier. The sheet models Bedrock inference (Claude Sonnet and Haiku), AgentCore, DynamoDB, S3, Lambda, and supporting services.
B8: 4. The 'Summary Dashboard' consolidates everything: total investment, total annual value, net benefit, ROI %, payback period, and a 3-year NPV. The bar chart shows cost vs. value by year.
B10: COLOR LEGEND
B11: Green cells | C11: Input cells — enter your institution's numbers here
B12: Blue cells | C12: Calculated cells — formula-driven; do not edit
B13: Orange cells | C13: Assumption cells — pre-filled with reference data; adjust as needed
B14: Yellow cells | C14: Section headers
B16: DISCLAIMER: All numbers in this calculator are illustrative. Actual outcomes depend on institution size, workflow volume, model selection, deployment configuration, and measured results from a properly baselined pilot. Reference outcomes (UA-Pulaski Tech, Highline College, Illinois Tech) are cited as peer benchmarks, not guarantees.

Sheet Institution Profile
B1: Institution Profile | C1: Your Value | D1: Notes
A2: INSTITUTION TYPE
B3: Institution type | C3: Community College
B4: Institution name (optional) | C4: [Your Institution]
A6: STUDENT ENROLLMENT
B7: Total student enrollment (headcount) | C7: 5000
B8: — of which: under 18 (K-12 or dual-enroll) | C8: 500
B9: Peak enrollment inquiry volume (monthly) | C9: 2000
B10: FAFSA / financial aid inquiries (monthly) | C10: 800
A12: STAFFING AND COST
B13: Total admin / student services FTE | C13: 12
B14: Total advising / counseling FTE | C14: 8
B15: Total IT / operations FTE | C15: 6
B16: Total faculty FTE | C16: 150
B17: Avg fully-loaded staff cost ($/hour) | C17: 45
B18: Avg fully-loaded faculty cost ($/hour) | C18: 65
A20: CURRENT WORKFLOW BASELINES
B21: Routine inquiry handling time (minutes/inquiry) | C21: 8
B22: Document processing cycle time (days, current) | C22: 14
B23: Students per advisor (current caseload) | C23: 250
B24: IT ticket mean time to resolve (hours) | C24: 18
B25: Grading hours per assignment (avg, faculty) | C25: 0.5
B26: % of inquiries received after business hours | C26: 0.3
B28: NOTE: These baseline numbers drive the ROI calculations on the 'Agent ROI' sheet. Capture your actual baseline data before the pilot — the pilot outcome is measured against these numbers.

Sheet Agent ROI
B1: Agent | C1: Deploy? | D1: Monthly Volume | E1: Deflection Rate | F1: Hours Saved/Mo | G1: Value/Month ($) | H1: One-Time Build ($)
B2: Agent 01 — Student & Family Services Concierge | C2: Y | D2: 2000 | E2: 0.65 | F2: =IF(C2="Y", D2*E2*('Institution Profile'!C21/60), 0) | G2: =IF(C2="Y", F2*'Institution Profile'!C17, 0) | H2: 95000
B3: Agent 02 — Personalized Tutor & Study Companion | C3: Y | D3: 500 | E3: 0.55 | F3: =IF(C3="Y", D3*E3*('Institution Profile'!C21/60), 0) | G3: =IF(C3="Y", F3*'Institution Profile'!C17, 0) | H3: 75000
B4: Agent 03 — Educator Copilot | C4: Y | D4: 300 | E4: 0.6 | F4: =IF(C4="Y", D4*E4*('Institution Profile'!C21/60), 0) | G4: =IF(C4="Y", F4*'Institution Profile'!C17, 0) | H4: 70000
B5: Agent 04 — Assessment, Grading & Feedback | C5: Y | D5: 200 | E5: 0.5 | F5: =IF(C5="Y", D5*E5*('Institution Profile'!C21/60), 0) | G5: =IF(C5="Y", F5*'Institution Profile'!C17, 0) | H5: 65000
B6: Agent 05 — Student Success & Proactive Engagement | C6: Y | D6: 400 | E6: 0.45 | F6: =IF(C6="Y", D6*E6*('Institution Profile'!C21/60), 0) | G6: =IF(C6="Y", F6*'Institution Profile'!C17, 0) | H6: 80000
B7: Agent 06 — Pathway Navigator | C7: Y | D7: 350 | E7: 0.5 | F7: =IF(C7="Y", D7*E7*('Institution Profile'!C21/60), 0) | G7: =IF(C7="Y", F7*'Institution Profile'!C17, 0) | H7: 70000
B8: Agent 07 — Document & Accessibility Services | C8: Y | D8: 600 | E8: 0.7 | F8: =IF(C8="Y", D8*E8*('Institution Profile'!C21/60), 0) | G8: =IF(C8="Y", F8*'Institution Profile'!C17, 0) | H8: 75000
B9: Agent 08 — Operations Service Desk | C9: Y | D9: 1200 | E9: 0.65 | F9: =IF(C9="Y", D9*E9*('Institution Profile'!C21/60), 0) | G9: =IF(C9="Y", F9*'Institution Profile'!C17, 0) | H9: 60000
A11: TOTALS
B12: Total hours saved / month (all active agents) | F12: =SUM(F2:F10) | G12: =SUM(G2:G10) | H12: =SUM(H2:H10)
B13: Total annual value (labor savings) | G13: =G12*12
B14: Total one-time build investment | H14: =H12
B16: NOTE — Build-once economics: The MCP gateway, identity, audit trail, and HITL framework are built once on the first agent. Agents 2–8 inherit them — the one-time build cost above reflects this amortization. The 'One-Time Build' for Agent 01 is the heaviest; subsequent agents are primarily connector + agent-specific logic.

Sheet AWS TCO
B1: AWS Service / Cost Element | C1: Unit | D1: Monthly Volume | E1: Rate ($/unit) | F1: Monthly Cost ($)
A2: BEDROCK INFERENCE
B3: Claude 3.5 Sonnet — input tokens | C3: per 1K tokens | D3: 5000 | E3: 0.003 | F3: =D3*E3
B4: Claude 3.5 Sonnet — output tokens | C4: per 1K tokens | D4: 2500 | E4: 0.015 | F4: =D4*E4
B5: Claude 3 Haiku — input tokens | C5: per 1K tokens | D5: 10000 | E5: 0.00025 | F5: =D5*E5
B6: Claude 3 Haiku — output tokens | C6: per 1K tokens | D6: 4000 | E6: 0.00125 | F6: =D6*E6
B7: Bedrock Knowledge Bases — queries | C7: per query | D7: 8000 | E7: 4e-06 | F7: =D7*E7
A8: AGENTCORE / GATEWAY
B9: AgentCore — invocations | C9: per invocation | D9: 1000000 | E9: 2.5e-06 | F9: =D9*E9
B10: AgentCore Identity — tokens minted | C10: per token | D10: 500000 | E10: 1e-06 | F10: =D10*E10
B11: API Gateway (Option B fallback) — requests | C11: per M requests | D11: 1 | E11: 3.5 | F11: =D11*E11
B12: Lambda — GB-seconds | C12: per GB-sec | D12: 500000 | E12: 1.66e-05 | F12: =D12*E12
B13: Step Functions — state transitions | C13: per 1K transitions | D13: 500 | E13: 0.025 | F13: =D13*E13
A14: STORAGE
B15: DynamoDB — on-demand reads (RRU) | C15: per M RRU | D15: 10 | E15: 0.125 | F15: =D15*E15
B16: DynamoDB — on-demand writes (WRU) | C16: per M WRU | D16: 5 | E16: 0.625 | F16: =D16*E16
B17: DynamoDB — storage (GB) | C17: GB/month | D17: 5 | E17: 0.25 | F17: =D17*E17
B18: S3 — Standard storage (GB) | C18: GB/month | D18: 50 | E18: 0.023 | F18: =D18*E18
B19: S3 — PUT/COPY/POST requests (per K) | C19: per K requests | D19: 100 | E19: 0.005 | F19: =D19*E19
B20: S3 Object Lock (audit WORM, GB) | C20: GB/month | D20: 10 | E20: 0.023 | F20: =D20*E20
A21: COMPUTE AND NETWORKING
B22: ECS Fargate — vCPU-hours/month | C22: vCPU-hours | D22: 720 | E22: 0.04048 | F22: =D22*E22
B23: ECS Fargate — GB memory-hours/month | C23: GB-hours | D23: 1440 | E23: 0.004445 | F23: =D23*E23
B24: Application Load Balancer — LCUs/hr | C24: LCU-hours | D24: 720 | E24: 0.008 | F24: =D24*E24
B25: NAT Gateway — GB processed | C25: GB | D25: 100 | E25: 0.045 | F25: =D25*E25
B26: CloudWatch — custom metrics | C26: per metric/mo | D26: 20 | E26: 0.3 | F26: =D26*E26
B27: CloudWatch — log ingestion (GB) | C27: GB | D27: 5 | E27: 0.5 | F27: =D27*E27
A28: SUPPORTING SERVICES
B29: KMS — API requests (per 10K) | C29: per 10K calls | D29: 100 | E29: 0.03 | F29: =D29*E29
B30: Secrets Manager — secrets/month | C30: per secret | D30: 10 | E30: 0.4 | F30: =D30*E30
B31: CloudTrail — events (per 100K) | C31: per 100K events | D31: 50 | E31: 0.1 | F31: =D31*E31
B32: Textract (Agent 07) — pages | C32: per page | D32: 1000 | E32: 0.0015 | F32: =D32*E32
B33: Translate (Agent 07) — per char (M) | C33: per M chars | D33: 1 | E33: 15 | F33: =D33*E33
B34: SES — emails sent | C34: per 1K emails | D34: 10 | E34: 0.1 | F34: =D34*E34
A36: TOTAL MONTHLY AWS COST
B37: Total monthly AWS infrastructure cost | F37: =SUM(F2:F35)
B38: Total annual AWS infrastructure cost | F38: =F37*12
B40: NOTE: Rates above reflect approximate list prices as of mid-2025. Actual rates depend on region, EDP/Reserved pricing, committed use discounts, and AWS pricing changes. Verify current rates at aws.amazon.com/pricing before presenting to a customer. Bedrock inference is typically the largest variable line — model at peak enrollment volume, not steady-state.

Sheet Summary Dashboard
B1: EDU AI Agent Suite — ROI Summary Dashboard
A3: INPUTS
B4: Discount rate for NPV calculation | C4: 0.08
A6: INVESTMENT SUMMARY
B7: Total one-time build investment (all agents) | C7: ='Agent ROI'!H19
B8: Annual AWS infrastructure run cost | C8: ='AWS TCO'!F47
B9: Annual managed service fee (SI — estimate) | C9: 120000
B10: Total annual run cost (AWS + managed service) | C10: =C8+C9
B11: Total 3-year total cost of ownership | C11: =C7+C10*3
A13: VALUE SUMMARY
B14: Total annual labor savings (all active agents) | C14: ='Agent ROI'!G20
B15: Service improvement value (% of labor savings — editable) | C15: 50000
B16: Total annual value (labor + service) | C16: =C14+C15
A18: ROI METRICS
B19: Net annual benefit (Value − Annual run cost) | C19: =C16-C10
B20: First-year ROI % | C20: =C16/C7
B21: Steady-state ROI % (year 2+) | C21: =C16/C10
B22: Payback period (months) | C22: =C7/MAX(C16-C10,1)*12
B23: 3-year NPV | C23: =C16/(1+C4)^1 + C16/(1+C4)^2 + C16/(1+C4)^3 - C7 - C10/(1+C4)^1 - C10/(1+C4)^2 - C10/(1+C4)^3
A25: 3-YEAR VIEW (for chart)
B26: Category | C26: Year 1 | D26: Year 2 | E26: Year 3
B27: Total Investment (build + run) | C27: =C7+C10 | D27: =C10 | E27: =C10
B28: Total Value (labor + service) | C28: =C16 | D28: =C16 | E28: =C16
B29: Net Benefit | C29: =C28-C27 | D29: =D28-D27 | E29: =E28-E27
B30: Cumulative Net Benefit | C30: =C29 | D30: =C29+D29 | E30: =C29+D29+E29
